Workbook

Sheet Budget
A1: Student Monthly Budget
A2: Type in the yellow cells. Totals update automatically.
A4: Income | B4: Planned | C4: Actual | D4: Difference
A5: Allowance / family support | B5: 0 | C5: 0 | D5: =C5-B5
A6: Part-time job | B6: 0 | C6: 0 | D6: =C6-B6
A7: Scholarship / bursary | B7: 0 | C7: 0 | D7: =C7-B7
A8: Other income | B8: 0 | C8: 0 | D8: =C8-B8
A9: Total income | B9: =SUM(B5:B8) | C9: =SUM(C5:C8) | D9: =SUM(D5:D8)
A11: Spending category | B11: Planned | C11: Actual (from Transactions) | D11: Difference
A12: Rent / hostel | B12: 0 | C12: =SUMIF(Transactions!$C:$C,A12,Transactions!$D:$D) | D12: =B12-C12
A13: Food | B13: 0 | C13: =SUMIF(Transactions!$C:$C,A13,Transactions!$D:$D) | D13: =B13-C13
A14: Transport | B14: 0 | C14: =SUMIF(Transactions!$C:$C,A14,Transactions!$D:$D) | D14: =B14-C14
A15: Books & supplies | B15: 0 | C15: =SUMIF(Transactions!$C:$C,A15,Transactions!$D:$D) | D15: =B15-C15
A16: Phone & data | B16: 0 | C16: =SUMIF(Transactions!$C:$C,A16,Transactions!$D:$D) | D16: =B16-C16
A17: Personal care | B17: 0 | C17: =SUMIF(Transactions!$C:$C,A17,Transactions!$D:$D) | D17: =B17-C17
A18: Entertainment | B18: 0 | C18: =SUMIF(Transactions!$C:$C,A18,Transactions!$D:$D) | D18: =B18-C18
A19: Savings | B19: 0 | C19: =SUMIF(Transactions!$C:$C,A19,Transactions!$D:$D) | D19: =B19-C19
A20: Other | B20: 0 | C20: =SUMIF(Transactions!$C:$C,A20,Transactions!$D:$D) | D20: =B20-C20
A21: Total spending | B21: =SUM(B12:B20) | C21: =SUM(C12:C20) | D21: =SUM(D12:D20)
A23: Remaining balance (actual income − actual spending) | C23: =C9-C21
A25: Template by OMT WORKING GROUP — free to use and adapt (CC BY 4.0).

Sheet Transactions
A1: Transactions
A2: Log each purchase. The Category must match a name on the Budget sheet.
A4: Date | B4: Description | C4: Category | D4: Amount
A5: 2026-10-01 | B5: Hostel fee (example — delete me) | C5: Rent / hostel | D5: 0
A6: 2026-10-02 | B6: Groceries (example — delete me) | C6: Food | D6: 0
